photoprotectionpy/__init__.py
photoprotectionpy/adjusted_spf.py
photoprotectionpy/critical_wavelength.py
photoprotectionpy/initial_spf.py
photoprotectionpy/uv_exposuredose.py
photoprotectionpy/uva_protectionfactor.py
photoprotectionpy-1.1.7.dist-info/METADATA
photoprotectionpy-1.1.7.dist-info/WHEEL
photoprotectionpy-1.1.7.dist-info/licenses/LICENSE.txt
photoprotectionpy-1.1.7.dist-info/RECORD
