Metadata-Version: 2.4
Name: photoprotectionpy
Version: 1.1.7
Summary: PhotoprotectionPy: In vitro sunscreen protector factor evaluation python package
Project-URL: Homepage, https://github.com/santiagohigareda/photoprotectionpy
Project-URL: Wiki, https://github.com/santiagohigareda/photoprotectionpy/wiki
Author-email: Santiago Guerrero-Higareda <a01636858@tec.mx>
License-Expression: Apache-2.0
License-File: LICENSE.txt
Keywords: ISO,SPF,UV,in vitro,photoprotection,skin,sunscreen
Classifier: License :: OSI Approved :: Apache Software License
Classifier: Operating System :: OS Independent
Classifier: Programming Language :: Python :: 3.9
Requires-Python: >=3.9
Requires-Dist: numpy
Requires-Dist: scipy
